profile_photo/__init__.py
profile_photo/__version__.py
profile_photo/errors.py
profile_photo/helpers.py
profile_photo/log.py
profile_photo/main.py
profile_photo/models.py
profile_photo/utils/__init__.py
profile_photo/utils/create_headshot.py
profile_photo/utils/dict_helper.py
profile_photo/utils/img_orient.py
profile_photo/utils/json_util.py
profile_photo/utils/aws/__init__.py
profile_photo/utils/aws/client_cache.py
profile_photo/utils/aws/rekognition.py
profile_photo/utils/aws/rekognition_models.py
profile_photo/utils/aws/rekognition_utils.py
profile_photo/utils/aws/s3.py
profile_photo-0.1.3.dist-info/LICENSE
profile_photo-0.1.3.dist-info/METADATA
profile_photo-0.1.3.dist-info/WHEEL
profile_photo-0.1.3.dist-info/top_level.txt
profile_photo-0.1.3.dist-info/RECORD
