Metadata-Version: 2.1
Name: profile-photo
Version: 0.1.3
Summary: Center + Crop Image to create a Profile Pic or Headshot
Home-page: https://github.com/rnag/profile-photo
Author: Ritvik Nag
Author-email: rv.kvetch@gmail.com
License: MIT
Project-URL: Documentation, https://profile-photo.readthedocs.io
Project-URL: Source, https://github.com/rnag/profile-photo
Keywords: profile,headshot,photo,crop,profile-photo,rekognition
Platform: UNKNOWN
Classifier: Development Status :: 2 - Pre-Alpha
Classifier: Intended Audience :: Developers
Classifier: License :: OSI Approved :: MIT License
Classifier: Natural Language :: English
Classifier: Programming Language :: Python :: 3 :: Only
Classifier: Programming Language :: Python :: 3
Classifier: Programming Language :: Python :: 3.8
Classifier: Programming Language :: Python :: 3.9
Classifier: Programming Language :: Python :: 3.10
Classifier: Programming Language :: Python :: 3.11
Classifier: Programming Language :: Python
Requires-Dist: opencv-python-headless (>=4.6.0.66)
Requires-Dist: dataclass-wizard (>=0.21.0)
Requires-Dist: pillow (>=9.3.0)
Provides-Extra: all
Requires-Dist: boto3 ; extra == 'all'
